setup.py
sps/__init__.py
sps/simple_pubsub.py
sps.egg-info/PKG-INFO
sps.egg-info/SOURCES.txt
sps.egg-info/dependency_links.txt
sps.egg-info/requires.txt
sps.egg-info/top_level.txt