Metadata-Version: 1.0
Name: sps
Version: 0.6.0
Summary: A simple pubsub framework (soon to be) with included REST API
Home-page: https://github.com/iLoveTux/simple_pubsub
Author: ilovetux
Author-email: me@ilovetux.com
License: GPL v2
Platform: UNKNOWN
